[
  {
    "name": "Git Workflow for Updating a Repo",
    "url": "https://docs.blackbaud.com/engineering-system-docs/learn/dev-setup-engsys/git-workflow",
    "icon": "git",
    "summary": "New to Git? Learn how to use Git process for updating your repo. The Engineering System has adopted Git as a standard version control for VSTS and GitHub."
  },
  {
    "name": "Learn How to Edit in VSTS",
    "path": "/learn/basics/vsts-editor/",
    "icon": "pencil-square-o",
    "summary": "Do you have a small edit? Learn how to use VSTS to make your change without leaving your web browser."
  },
  {
    "name": "Branch Policies and Security in VSTS",
    "path": "/learn/get-started/vsts-repo-setup",
    "icon": "shield",
    "summary": "VSTS Git Repos are set up with standard policies. If necessary, learn how to edit them for your Stache SPA."
  }
]
